sagemath_mcqd-10.5.dist-info/top_level.txt
sagemath_mcqd-10.5.dist-info/RECORD
sagemath_mcqd-10.5.dist-info/METADATA
sagemath_mcqd-10.5.dist-info/WHEEL
sage/all__sagemath_mcqd.py
sage/graphs/mcqd.pxd
sage/graphs/all__sagemath_mcqd.py
sage/graphs/mcqd.cpython-312-i386-linux-musl.so
sage/graphs/mcqd.pyx
sage/cython_debug/cython_debug_info_sage.graphs.mcqd
sage/cython_debug/interpreter
sagemath_mcqd.libs/libstdc++-d2a021ba.so.6.0.32
sagemath_mcqd.libs/libgcc_s-f3fb5a36.so.1
